{
  "isPromise": true,
  "volume": "Seeker.slowGrep",
  "args": [
    {
      "pattern": "\\b(d|ḍ)ev(a|ā)(d|ḍ)(a|ā)(t|ṭ)(t|ṭ)(a|ā)",
      "maxResults": 1000,
      "lang": "pli",
      "reTipCat": {},
      "root": "local/ebt-data",
      "patPrimary": "/sutta/"
    }
  ],
  "value": [
    "root/pli/ms/sutta/kn/mil/mil5.1.3_root-pli-ms.json:20",
    "root/pli/ms/sutta/an/an4/an4.68_root-pli-ms.json:8",
    "root/pli/ms/sutta/sn/sn17/sn17.35_root-pli-ms.json:6",
    "root/pli/ms/sutta/an/an6/an6.62_root-pli-ms.json:6",
    "root/pli/ms/sutta/sn/sn17/sn17.36_root-pli-ms.json:5",
    "root/pli/ms/sutta/kn/mil/mil5.4.7_root-pli-ms.json:3",
    "root/pli/ms/sutta/sn/sn6/sn6.12_root-pli-ms.json:2",
    "root/pli/ms/sutta/kn/mil/mil5.3.8_root-pli-ms.json:2",
    "root/pli/ms/sutta/kn/dhp/dhp1-20_root-pli-ms.json:2",
    "root/pli/ms/sutta/an/an8/an8.7_root-pli-ms.json:2",
    "root/pli/ms/sutta/an/an5/an5.100_root-pli-ms.json:2",
    "root/pli/ms/sutta/sn/sn17/sn17.34_root-pli-ms.json:1",
    "root/pli/ms/sutta/sn/sn17/sn17.33_root-pli-ms.json:1",
    "root/pli/ms/sutta/sn/sn17/sn17.32_root-pli-ms.json:1",
    "root/pli/ms/sutta/sn/sn14/sn14.15_root-pli-ms.json:1",
    "root/pli/ms/sutta/mn/mn29_root-pli-ms.json:1",
    "root/pli/ms/sutta/kn/tha-ap/tha-ap537_root-pli-ms.json:1",
    "root/pli/ms/sutta/kn/ne/ne21_root-pli-ms.json:1",
    "root/pli/ms/sutta/kn/mil/mil7.7.5_root-pli-ms.json:1",
    "root/pli/ms/sutta/kn/iti/vagga9/iti89_root-pli-ms.json:1",
    "root/pli/ms/sutta/kn/dhp/dhp157-166_root-pli-ms.json:1",
    "root/pli/ms/sutta/an/an8/an8.8_root-pli-ms.json:1"
  ]
}