{
  "isPromise": true,
  "volume": "Seeker.callSlowFind",
  "args": [
    {
      "pattern": "i’m better",
      "showMatchesOnly": true,
      "languages": [
        "pli",
        "en"
      ],
      "maxResults": 1000,
      "searchLang": "en",
      "maxDoc": 50,
      "minLang": 2,
      "matchHighlight": "<span class=\"ebt-matched\">$&</span>",
      "lang": "en",
      "types": [
        "root",
        "translation"
      ],
      "includeUnpublished": false
    }
  ],
  "value": {
    "lang": "en",
    "searchLang": "en",
    "minLang": 2,
    "maxDoc": 50,
    "maxResults": 1000,
    "pattern": "i’m better",
    "method": "phrase",
    "resultPattern": "\\bi’m better",
    "segsMatched": 17,
    "bilaraPaths": [
      "root/pli/ms/sutta/sn/sn35/sn35.108_root-pli-ms.json",
      "translation/en/sujato/sutta/sn/sn35/sn35.108_translation-en-sujato.json",
      "root/pli/ms/sutta/sn/sn22/sn22.49_root-pli-ms.json",
      "translation/en/sujato/sutta/sn/sn22/sn22.49_translation-en-sujato.json",
      "root/pli/ms/sutta/an/an4/an4.185_root-pli-ms.json",
      "translation/en/sujato/sutta/an/an4/an4.185_translation-en-sujato.json",
      "root/pli/ms/sutta/sn/sn45/sn45.162_root-pli-ms.json",
      "translation/en/sujato/sutta/sn/sn45/sn45.162_translation-en-sujato.json",
      "root/pli/ms/sutta/kn/thag/thag18.1_root-pli-ms.json",
      "translation/en/sujato/sutta/kn/thag/thag18.1_translation-en-sujato.json",
      "root/pli/ms/sutta/dn/dn33_root-pli-ms.json",
      "translation/en/sujato/sutta/dn/dn33_translation-en-sujato.json"
    ],
    "suttaRefs": [
      "sn35.108/en/sujato",
      "sn22.49/en/sujato",
      "an4.185/en/sujato",
      "sn45.162/en/sujato",
      "thag18.1/en/sujato",
      "dn33/en/sujato"
    ],
    "mlDocs": [
      {
        "bilaraPaths": [
          "root/pli/ms/sutta/sn/sn35/sn35.108_root-pli-ms.json",
          "translation/en/sujato/sutta/sn/sn35/sn35.108_translation-en-sujato.json"
        ],
        "author_uid": "sujato",
        "type": "translation",
        "category": "sutta",
        "sutta_uid": "sn35.108",
        "lang": "en",
        "segMap": {
          "sn35.108:0.3": {
            "scid": "sn35.108:0.3",
            "pli": "108. Seyyohamasmisutta ",
            "en": "108. <span class=\"ebt-matched\">I’m Better</span> ",
            "matched": true
          },
          "sn35.108:1.1": {
            "scid": "sn35.108:1.1",
            "pli": "“Kismiṁ nu kho, bhikkhave, sati kiṁ upādāya kiṁ abhinivissa seyyohamasmīti vā hoti, sadisohamasmīti vā hoti, hīnohamasmīti vā hotī”ti? ",
            "en": "“Mendicants, when what exists, because of grasping what and insisting on what, do people think ‘<span class=\"ebt-matched\">I’m better</span>’ or ‘I’m equal’ or ‘I’m worse’?” ",
            "matched": true
          },
          "sn35.108:3.1": {
            "scid": "sn35.108:3.1",
            "pli": "“Cakkhusmiṁ kho, bhikkhave, sati cakkhuṁ upādāya cakkhuṁ abhinivissa seyyohamasmīti vā hoti, sadisohamasmīti vā hoti, hīnohamasmīti vā hoti …pe… ",
            "en": "“When there’s an eye, because of grasping the eye and insisting on the eye, people think ‘<span class=\"ebt-matched\">I’m better</span>’ or ‘I’m equal’ or ‘I’m worse’. … ",
            "matched": true
          },
          "sn35.108:3.3": {
            "scid": "sn35.108:3.3",
            "pli": "manasmiṁ sati manaṁ upādāya manaṁ abhinivissa seyyohamasmīti vā hoti, sadisohamasmīti vā hoti, hīnohamasmīti vā hoti. ",
            "en": "When there’s a mind, because of grasping the mind and insisting on the mind, people think ‘<span class=\"ebt-matched\">I’m better</span>’ or ‘I’m equal’ or ‘I’m worse’. ",
            "matched": true
          },
          "sn35.108:7.1": {
            "scid": "sn35.108:7.1",
            "pli": "“Yaṁ panāniccaṁ dukkhaṁ vipariṇāmadhammaṁ, api nu taṁ anupādāya seyyohamasmīti vā assa, sadisohamasmīti vā assa, hīnohamasmīti vā assā”ti? ",
            "en": "“But by not grasping what’s impermanent, suffering, and perishable, would people think ‘<span class=\"ebt-matched\">I’m better</span>’ or ‘I’m equal’ or ‘I’m worse’?” ",
            "matched": true
          },
          "sn35.108:14.1": {
            "scid": "sn35.108:14.1",
            "pli": "“Yaṁ panāniccaṁ dukkhaṁ vipariṇāmadhammaṁ, api nu taṁ anupādāya seyyohamasmīti vā assa, sadisohamasmīti vā assa, hīnohamasmīti vā assā”ti? ",
            "en": "“But by not grasping what’s impermanent, suffering, and perishable, would people think ‘<span class=\"ebt-matched\">I’m better</span>’ or ‘I’m equal’ or ‘I’m worse’?” ",
            "matched": true
          }
        },
        "score": 6.214,
        "hyphen": "­",
        "maxWord": 30,
        "minWord": 5,
        "title": "Linked Discourses 35\n11. Sanctuary\n108. I’m Better",
        "segsMatched": 6,
        "langSegs": {
          "pli": 28,
          "en": 27
        }
      },
      {
        "bilaraPaths": [
          "root/pli/ms/sutta/sn/sn22/sn22.49_root-pli-ms.json",
          "translation/en/sujato/sutta/sn/sn22/sn22.49_translation-en-sujato.json"
        ],
        "author_uid": "sujato",
        "type": "translation",
        "category": "sutta",
        "sutta_uid": "sn22.49",
        "lang": "en",
        "segMap": {
          "sn22.49:2.1": {
            "scid": "sn22.49:2.1",
            "pli": "“Ye hi keci, soṇa, samaṇā vā brāhmaṇā vā aniccena rūpena dukkhena vipariṇāmadhammena ‘seyyohamasmī’ti vā samanupassanti; ",
            "en": "“Soṇa, there are ascetics and brahmins who—based on form, which is impermanent, suffering, and perishable—regard themselves thus: ‘<span class=\"ebt-matched\">I’m better</span>’, ",
            "matched": true
          },
          "sn22.49:2.14": {
            "scid": "sn22.49:2.14",
            "pli": "Aniccena viññāṇena dukkhena vipariṇāmadhammena ‘seyyohamasmī’ti vā samanupassanti; ",
            "en": "consciousness, which is impermanent, suffering, and perishable, they regard themselves thus: ‘<span class=\"ebt-matched\">I’m better</span>’, ",
            "matched": true
          },
          "sn22.49:3.1": {
            "scid": "sn22.49:3.1",
            "pli": "Ye ca kho keci, soṇa, samaṇā vā brāhmaṇā vā aniccena rūpena dukkhena vipariṇāmadhammena ‘seyyohamasmī’tipi na samanupassanti; ",
            "en": "There are ascetics and brahmins who—based on form, which is impermanent, suffering, and perishable—don’t regard themselves thus: ‘<span class=\"ebt-matched\">I’m better</span>’, ",
            "matched": true
          },
          "sn22.49:3.8": {
            "scid": "sn22.49:3.8",
            "pli": "aniccena viññāṇena dukkhena vipariṇāmadhammena ‘seyyohamasmī’tipi na samanupassanti; ",
            "en": "consciousness, which is impermanent, suffering, and perishable, they don’t regard themselves thus: ‘<span class=\"ebt-matched\">I’m better</span>’, ",
            "matched": true
          }
        },
        "score": 4.063,
        "hyphen": "­",
        "maxWord": 30,
        "minWord": 5,
        "title": "Linked Discourses 22\n5. Be Your Own Island\n49. With Soṇa",
        "segsMatched": 4,
        "langSegs": {
          "pli": 63,
          "en": 62
        }
      },
      {
        "bilaraPaths": [
          "root/pli/ms/sutta/an/an4/an4.185_root-pli-ms.json",
          "translation/en/sujato/sutta/an/an4/an4.185_translation-en-sujato.json"
        ],
        "author_uid": "sujato",
        "type": "translation",
        "category": "sutta",
        "sutta_uid": "an4.185",
        "lang": "en",
        "segMap": {
          "an4.185:4.6": {
            "scid": "an4.185:4.6",
            "pli": "So tena na samaṇoti maññati, na brāhmaṇoti maññati, na seyyohamasmīti maññati, na sadisohamasmīti maññati, na hīnohamasmīti maññati. ",
            "en": "But they don’t think of themselves as an ‘ascetic’ or ‘brahmin’ because of that. Nor do they think ‘<span class=\"ebt-matched\">I’m better</span>’ or ‘I’m equal’ or ‘I’m worse’. ",
            "matched": true
          },
          "an4.185:5.4": {
            "scid": "an4.185:5.4",
            "pli": "So tena na samaṇoti maññati, na brāhmaṇoti maññati, na seyyohamasmīti maññati, na sadisohamasmīti maññati, na hīnohamasmīti maññati. ",
            "en": "But they don’t think of themselves as an ‘ascetic’ or ‘brahmin’ because of that. Nor do they think ‘<span class=\"ebt-matched\">I’m better</span>’ or ‘I’m equal’ or ‘I’m worse’. ",
            "matched": true
          },
          "an4.185:7.4": {
            "scid": "an4.185:7.4",
            "pli": "So tena na samaṇoti maññati, na brāhmaṇoti maññati, na seyyohamasmīti maññati, na sadisohamasmīti maññati, na hīnohamasmīti maññati. ",
            "en": "But they don’t think of themselves as an ‘ascetic’ or ‘brahmin’ because of that. Nor do they think ‘<span class=\"ebt-matched\">I’m better</span>’ or ‘I’m equal’ or ‘I’m worse’. ",
            "matched": true
          }
        },
        "score": 3.091,
        "hyphen": "­",
        "maxWord": 30,
        "minWord": 5,
        "title": "Numbered Discourses 4\n19. Brahmins\n185. Truths of the Brahmins",
        "segsMatched": 3,
        "langSegs": {
          "pli": 33,
          "en": 32
        }
      },
      {
        "bilaraPaths": [
          "root/pli/ms/sutta/kn/thag/thag18.1_root-pli-ms.json",
          "translation/en/sujato/sutta/kn/thag/thag18.1_translation-en-sujato.json"
        ],
        "author_uid": "sujato",
        "type": "translation",
        "category": "sutta",
        "sutta_uid": "thag18.1",
        "lang": "en",
        "segMap": {
          "thag18.1:24.4": {
            "scid": "thag18.1:24.4",
            "pli": "ahaṁ seyyoti maññati.",
            "en": "and thinking, ‘<span class=\"ebt-matched\">I’m better</span> than them.’",
            "matched": true
          },
          "thag18.1:26.3": {
            "scid": "thag18.1:26.3",
            "pli": "Hīno taṁsadiso vāti,",
            "en": "‘I am better’, ‘I’m not better’,",
            "matched": true
          }
        },
        "score": 2.011,
        "hyphen": "­",
        "maxWord": 30,
        "minWord": 5,
        "title": "Verses of the Senior Monks\nThe Book of the Forties\nChapter One\n18.1. Mahākassapa",
        "segsMatched": 2,
        "langSegs": {
          "pli": 178,
          "en": 170
        }
      },
      {
        "bilaraPaths": [
          "root/pli/ms/sutta/sn/sn45/sn45.162_root-pli-ms.json",
          "translation/en/sujato/sutta/sn/sn45/sn45.162_translation-en-sujato.json"
        ],
        "author_uid": "sujato",
        "type": "translation",
        "category": "sutta",
        "sutta_uid": "sn45.162",
        "lang": "en",
        "segMap": {
          "sn45.162:1.3": {
            "scid": "sn45.162:1.3",
            "pli": "‘Seyyohamasmī’ti vidhā, ‘sadisohamasmī’ti vidhā, ‘hīnohamasmī’ti vidhā—",
            "en": "One discriminates, thinking that ‘<span class=\"ebt-matched\">I’m better</span>’ or ‘I’m equal’ or ‘I’m worse’. ",
            "matched": true
          }
        },
        "score": 1.077,
        "hyphen": "­",
        "maxWord": 30,
        "minWord": 5,
        "title": "Linked Discourses 45\n13. Searches\n162. Discriminations",
        "segsMatched": 1,
        "langSegs": {
          "pli": 13,
          "en": 12
        }
      },
      {
        "bilaraPaths": [
          "root/pli/ms/sutta/dn/dn33_root-pli-ms.json",
          "translation/en/sujato/sutta/dn/dn33_translation-en-sujato.json"
        ],
        "author_uid": "sujato",
        "type": "translation",
        "category": "sutta",
        "sutta_uid": "dn33",
        "lang": "en",
        "segMap": {
          "dn33:1.10.49": {
            "scid": "dn33:1.10.49",
            "pli": "seyyohamasmīti vidhā, sadisohamasmīti vidhā, hīnohamasmīti vidhā. ",
            "en": "‘<span class=\"ebt-matched\">I’m better</span>’, ‘I’m equal’, and ‘I’m worse’. ",
            "matched": true
          }
        },
        "score": 1.001,
        "hyphen": "­",
        "maxWord": 30,
        "minWord": 5,
        "title": "Long Discourses 33\nReciting in Concert",
        "segsMatched": 1,
        "langSegs": {
          "pli": 1167,
          "en": 1166
        }
      }
    ]
  }
}