{
  "isPromise": true,
  "volume": "Seeker.callSlowFind",
  "args": [
    {
      "pattern": "sei deine eigene insel",
      "showMatchesOnly": true,
      "languages": [
        "pli",
        "en",
        "de"
      ],
      "maxResults": 1000,
      "searchLang": "de",
      "maxDoc": 50,
      "minLang": 3,
      "matchHighlight": "<span class=\"ebt-matched\">$&</span>",
      "lang": "de",
      "types": [
        "root",
        "translation"
      ],
      "includeUnpublished": false
    }
  ],
  "value": {
    "lang": "de",
    "searchLang": "de",
    "minLang": 3,
    "maxDoc": 50,
    "maxResults": 1000,
    "pattern": "sei deine eigene insel",
    "method": "keywords",
    "resultPattern": "\\bsei|\\bdeine|\\beigene|\\binsel",
    "segsMatched": 2,
    "bilaraPaths": [
      "root/pli/ms/sutta/sn/sn47/sn47.13_root-pli-ms.json",
      "translation/de/sabbamitta/sutta/sn/sn47/sn47.13_translation-de-sabbamitta.json",
      "translation/en/sujato/sutta/sn/sn47/sn47.13_translation-en-sujato.json",
      "root/pli/ms/sutta/sn/sn47/sn47.9_root-pli-ms.json",
      "translation/de/sabbamitta/sutta/sn/sn47/sn47.9_translation-de-sabbamitta.json",
      "translation/en/sujato/sutta/sn/sn47/sn47.9_translation-en-sujato.json"
    ],
    "suttaRefs": [
      "sn47.13/de/sabbamitta",
      "sn47.9/de/sabbamitta"
    ],
    "mlDocs": [
      {
        "bilaraPaths": [
          "root/pli/ms/sutta/sn/sn47/sn47.13_root-pli-ms.json",
          "translation/de/sabbamitta/sutta/sn/sn47/sn47.13_translation-de-sabbamitta.json",
          "translation/en/sujato/sutta/sn/sn47/sn47.13_translation-en-sujato.json"
        ],
        "author_uid": "sabbamitta",
        "type": "translation",
        "category": "sutta",
        "sutta_uid": "sn47.13",
        "lang": "de",
        "segMap": {
          "sn47.13:6.9": {
            "scid": "sn47.13:6.9",
            "pli": "Tasmātihānanda, attadīpā viharatha attasaraṇā anaññasaraṇā, dhammadīpā dhammasaraṇā anaññasaraṇā. ",
            "de": "Daher, Ānanda, lebe als <span class=\"ebt-matched\">deine</span> <span class=\"ebt-matched\">eigene</span> <span class=\"ebt-matched\">Insel</span>, als <span class=\"ebt-matched\">deine</span> <span class=\"ebt-matched\">eigene</span> Zuflucht, suche keine andere Zuflucht. Lass die Lehre <span class=\"ebt-matched\">deine</span> <span class=\"ebt-matched\">Insel</span> und <span class=\"ebt-matched\">deine</span> Zuflucht <span class=\"ebt-matched\">sei</span>n, suche keine andere Zuflucht. ",
            "en": "So Ānanda, be your own island, your own refuge, with no other refuge. Let the teaching be your island and your refuge, with no other refuge. ",
            "matched": true
          }
        },
        "score": 1.024,
        "hyphen": "­",
        "maxWord": 30,
        "minWord": 5,
        "title": "Verbundene Lehrreden 47\n2. Bei Nālandā\n13. Mit Cunda",
        "segsMatched": 1,
        "langSegs": {
          "pli": 42,
          "de": 38,
          "en": 41
        }
      },
      {
        "bilaraPaths": [
          "root/pli/ms/sutta/sn/sn47/sn47.9_root-pli-ms.json",
          "translation/de/sabbamitta/sutta/sn/sn47/sn47.9_translation-de-sabbamitta.json",
          "translation/en/sujato/sutta/sn/sn47/sn47.9_translation-en-sujato.json"
        ],
        "author_uid": "sabbamitta",
        "type": "translation",
        "category": "sutta",
        "sutta_uid": "sn47.9",
        "lang": "de",
        "segMap": {
          "sn47.9:5.2": {
            "scid": "sn47.9:5.2",
            "pli": "Tasmātihānanda, attadīpā viharatha attasaraṇā anaññasaraṇā, dhammadīpā dhammasaraṇā anaññasaraṇā. ",
            "de": "Daher, Ānanda, lebe als <span class=\"ebt-matched\">deine</span> <span class=\"ebt-matched\">eigene</span> <span class=\"ebt-matched\">Insel</span>, als <span class=\"ebt-matched\">deine</span> <span class=\"ebt-matched\">eigene</span> Zuflucht, suche keine andere Zuflucht. Lass die Lehre <span class=\"ebt-matched\">deine</span> <span class=\"ebt-matched\">Insel</span> und <span class=\"ebt-matched\">deine</span> Zuflucht <span class=\"ebt-matched\">sei</span>n, suche keine andere Zuflucht. ",
            "en": "So Ānanda, be your own island, your own refuge, with no other refuge. Let the teaching be your island and your refuge, with no other refuge. ",
            "matched": true
          }
        },
        "score": 1.021,
        "hyphen": "­",
        "maxWord": 30,
        "minWord": 5,
        "title": "Verbundene Lehrreden 47\n1. In Ambapālīs Wald\n9. Krank",
        "segsMatched": 1,
        "langSegs": {
          "pli": 47,
          "de": 45,
          "en": 46
        }
      }
    ]
  }
}