{
  "isPromise": true,
  "volume": "Seeker.callSlowFind",
  "args": [
    {
      "pattern": "take the wealth",
      "showMatchesOnly": true,
      "languages": [
        "pli",
        "en"
      ],
      "maxResults": 1000,
      "searchLang": "en",
      "maxDoc": 50,
      "minLang": 2,
      "matchHighlight": "<span class=\"ebt-matched\">$&</span>",
      "lang": "en",
      "types": [
        "root",
        "translation"
      ],
      "includeUnpublished": false
    }
  ],
  "value": {
    "lang": "en",
    "searchLang": "en",
    "minLang": 2,
    "maxDoc": 50,
    "maxResults": 1000,
    "pattern": "take the wealth",
    "method": "phrase",
    "resultPattern": "\\btake the wealth",
    "segsMatched": 10,
    "bilaraPaths": [
      "root/pli/ms/sutta/mn/mn41_root-pli-ms.json",
      "translation/en/sujato/sutta/mn/mn41_translation-en-sujato.json",
      "root/pli/ms/sutta/mn/mn114_root-pli-ms.json",
      "translation/en/sujato/sutta/mn/mn114_translation-en-sujato.json",
      "root/pli/ms/sutta/an/an10/an10.217_root-pli-ms.json",
      "translation/en/sujato/sutta/an/an10/an10.217_translation-en-sujato.json",
      "root/pli/ms/sutta/an/an10/an10.211_root-pli-ms.json",
      "translation/en/sujato/sutta/an/an10/an10.211_translation-en-sujato.json",
      "root/pli/ms/sutta/an/an10/an10.176_root-pli-ms.json",
      "translation/en/sujato/sutta/an/an10/an10.176_translation-en-sujato.json"
    ],
    "suttaRefs": [
      "mn41/en/sujato",
      "mn114/en/sujato",
      "an10.217/en/sujato",
      "an10.211/en/sujato",
      "an10.176/en/sujato"
    ],
    "mlDocs": [
      {
        "bilaraPaths": [
          "root/pli/ms/sutta/an/an10/an10.211_root-pli-ms.json",
          "translation/en/sujato/sutta/an/an10/an10.211_translation-en-sujato.json"
        ],
        "author_uid": "sujato",
        "type": "translation",
        "category": "sutta",
        "sutta_uid": "an10.211",
        "lang": "en",
        "segMap": {
          "an10.211:2.1": {
            "scid": "an10.211:2.1",
            "pli": "Adinnādāyī hoti, yaṁ taṁ parassa paravittūpakaraṇaṁ gāmagataṁ vā araññagataṁ vā, taṁ adinnaṁ theyyasaṅkhātaṁ ādātā hoti. ",
            "en": "They steal. With the intention to commit theft, they <span class=\"ebt-matched\">take the wealth</span> or belongings of others from village or wilderness. ",
            "matched": true
          },
          "an10.211:13.1": {
            "scid": "an10.211:13.1",
            "pli": "Adinnādānaṁ pahāya adinnādānā paṭivirato hoti. Yaṁ taṁ parassa paravittūpakaraṇaṁ gāmagataṁ vā araññagataṁ vā, na taṁ adinnaṁ theyyasaṅkhātaṁ ādātā hoti. ",
            "en": "They give up stealing. They don’t, with the intention to commit theft, <span class=\"ebt-matched\">take the wealth</span> or belongings of others from village or wilderness. ",
            "matched": true
          }
        },
        "score": 2.063,
        "hyphen": "­",
        "maxWord": 30,
        "minWord": 5,
        "title": "Numbered Discourses 10\n21. The Body Born of Deeds\n211. Heaven and Hell (1st)",
        "segsMatched": 2,
        "langSegs": {
          "pli": 32,
          "en": 31
        }
      },
      {
        "bilaraPaths": [
          "root/pli/ms/sutta/an/an10/an10.217_root-pli-ms.json",
          "translation/en/sujato/sutta/an/an10/an10.217_translation-en-sujato.json"
        ],
        "author_uid": "sujato",
        "type": "translation",
        "category": "sutta",
        "sutta_uid": "an10.217",
        "lang": "en",
        "segMap": {
          "an10.217:4.1": {
            "scid": "an10.217:4.1",
            "pli": "Adinnādāyī hoti, yaṁ taṁ parassa paravittūpakaraṇaṁ gāmagataṁ vā araññagataṁ vā, taṁ adinnaṁ theyyasaṅkhātaṁ ādātā hoti. ",
            "en": "They steal. With the intention to commit theft, they <span class=\"ebt-matched\">take the wealth</span> or belongings of others from village or wilderness. ",
            "matched": true
          },
          "an10.217:21.1": {
            "scid": "an10.217:21.1",
            "pli": "Adinnādānā paṭivirato hoti, yaṁ taṁ parassa paravittūpakaraṇaṁ gāmagataṁ vā araññagataṁ vā, na taṁ adinnaṁ theyyasaṅkhātaṁ ādātā hoti. ",
            "en": "They don’t steal. They don’t, with the intention to commit theft, <span class=\"ebt-matched\">take the wealth</span> or belongings of others from village or wilderness. ",
            "matched": true
          }
        },
        "score": 2.033,
        "hyphen": "­",
        "maxWord": 30,
        "minWord": 5,
        "title": "Numbered Discourses 10\n21. The Body Born of Deeds\n217. Intentional (1st)",
        "segsMatched": 2,
        "langSegs": {
          "pli": 60,
          "en": 59
        }
      },
      {
        "bilaraPaths": [
          "root/pli/ms/sutta/an/an10/an10.176_root-pli-ms.json",
          "translation/en/sujato/sutta/an/an10/an10.176_translation-en-sujato.json"
        ],
        "author_uid": "sujato",
        "type": "translation",
        "category": "sutta",
        "sutta_uid": "an10.176",
        "lang": "en",
        "segMap": {
          "an10.176:7.1": {
            "scid": "an10.176:7.1",
            "pli": "Adinnādāyī hoti. Yaṁ taṁ parassa paravittūpakaraṇaṁ gāmagataṁ vā araññagataṁ vā taṁ adinnaṁ theyyasaṅkhātaṁ ādātā hoti. ",
            "en": "They steal. With the intention to commit theft, they <span class=\"ebt-matched\">take the wealth</span> or belongings of others from village or wilderness. ",
            "matched": true
          },
          "an10.176:26.1": {
            "scid": "an10.176:26.1",
            "pli": "Adinnādānaṁ pahāya, adinnādānā paṭivirato hoti. Yaṁ taṁ parassa paravittūpakaraṇaṁ gāmagataṁ vā araññagataṁ vā, na taṁ adinnaṁ theyyasaṅkhātaṁ ādātā hoti. ",
            "en": "They give up stealing. They don’t, with the intention to commit theft, <span class=\"ebt-matched\">take the wealth</span> or belongings of others from village or wilderness. ",
            "matched": true
          }
        },
        "score": 2.023,
        "hyphen": "­",
        "maxWord": 30,
        "minWord": 5,
        "title": "Numbered Discourses 10\n17. With Jāṇussoṇi\n176. With Cunda",
        "segsMatched": 2,
        "langSegs": {
          "pli": 88,
          "en": 87
        }
      },
      {
        "bilaraPaths": [
          "root/pli/ms/sutta/mn/mn41_root-pli-ms.json",
          "translation/en/sujato/sutta/mn/mn41_translation-en-sujato.json"
        ],
        "author_uid": "sujato",
        "type": "translation",
        "category": "sutta",
        "sutta_uid": "mn41",
        "lang": "en",
        "segMap": {
          "mn41:8.3": {
            "scid": "mn41:8.3",
            "pli": "Adinnādāyī kho pana hoti. Yaṁ taṁ parassa paravittūpakaraṇaṁ, gāmagataṁ vā araññagataṁ vā, taṁ adinnaṁ theyyasaṅkhātaṁ ādātā hoti. ",
            "en": "They steal. With the intention to commit theft, they <span class=\"ebt-matched\">take the wealth</span> or belongings of others from village or wilderness. ",
            "matched": true
          },
          "mn41:12.3": {
            "scid": "mn41:12.3",
            "pli": "Adinnādānaṁ pahāya adinnādānā paṭivirato hoti. Yaṁ taṁ parassa paravittūpakaraṇaṁ, gāmagataṁ vā araññagataṁ vā, taṁ nādinnaṁ theyyasaṅkhātaṁ ādātā hoti. ",
            "en": "They give up stealing. They don’t, with the intention to commit theft, <span class=\"ebt-matched\">take the wealth</span> or belongings of others from village or wilderness. ",
            "matched": true
          }
        },
        "score": 2.016,
        "hyphen": "­",
        "maxWord": 30,
        "minWord": 5,
        "title": "Middle Discourses 41\nThe People of Sālā",
        "segsMatched": 2,
        "langSegs": {
          "pli": 122,
          "en": 121
        }
      },
      {
        "bilaraPaths": [
          "root/pli/ms/sutta/mn/mn114_root-pli-ms.json",
          "translation/en/sujato/sutta/mn/mn114_translation-en-sujato.json"
        ],
        "author_uid": "sujato",
        "type": "translation",
        "category": "sutta",
        "sutta_uid": "mn114",
        "lang": "en",
        "segMap": {
          "mn114:5.10": {
            "scid": "mn114:5.10",
            "pli": "adinnādāyī kho pana hoti, yaṁ taṁ parassa paravittūpakaraṇaṁ gāmagataṁ vā araññagataṁ vā taṁ adinnaṁ theyyasaṅkhātaṁ ādātā hoti; ",
            "en": "They steal. With the intention to commit theft, they <span class=\"ebt-matched\">take the wealth</span> or belongings of others from village or wilderness. ",
            "matched": true
          },
          "mn114:5.15": {
            "scid": "mn114:5.15",
            "pli": "adinnādānaṁ pahāya adinnādānā paṭivirato hoti, yaṁ taṁ parassa paravittūpakaraṇaṁ gāmagataṁ vā araññagataṁ vā taṁ nādinnaṁ theyyasaṅkhātaṁ ādātā hoti; ",
            "en": "They give up stealing. They don’t, with the intention to commit theft, <span class=\"ebt-matched\">take the wealth</span> or belongings of others from village or wilderness. ",
            "matched": true
          }
        },
        "score": 2.005,
        "hyphen": "­",
        "maxWord": 30,
        "minWord": 5,
        "title": "Middle Discourses 114\nWhat Should and Should Not Be Cultivated",
        "segsMatched": 2,
        "langSegs": {
          "pli": 373,
          "en": 372
        }
      }
    ]
  }
}