{
  "isPromise": true,
  "volume": "Seeker.slowGrep",
  "args": [
    {
      "pattern": "\\bnever be content",
      "maxResults": 1000,
      "lang": "en",
      "reTipCat": {},
      "root": "local/ebt-data",
      "patPrimary": "/sutta/"
    }
  ],
  "value": [
    "translation/en/sujato/sutta/dn/dn33_translation-en-sujato.json:1",
    "translation/en/sujato/sutta/an/an2/an2.163-179_translation-en-sujato.json:1",
    "translation/en/sujato/sutta/an/an2/an2.1-10_translation-en-sujato.json:1"
  ]
}